desktop.ini
myprimelib9b/__init__.py
myprimelib9b/desktop.ini
myprimelib9b/prime_numbers.py
myprimelib9b/prime_numbersNew.py
myprimelib9b-0.0.3.dist-info/LICENSE
myprimelib9b-0.0.3.dist-info/METADATA
myprimelib9b-0.0.3.dist-info/WHEEL
myprimelib9b-0.0.3.dist-info/top_level.txt
myprimelib9b-0.0.3.dist-info/RECORD
