Metadata-Version: 2.1
Name: myprimelib9b
Version: 0.0.3
Summary: Create A small package to work with prime numbers
Home-page: https://github.com/myNKUST/myprimelib9b.git
Author: timenet2300
Author-email: timenet2300@gmail.com
Classifier: Programming Language :: Python :: 3
Classifier: License :: OSI Approved :: MIT License
Classifier: Operating System :: OS Independent
License-File: LICENSE
